rstarexx-1.0.dist-info/licenses/LICENSE
starexx/__init__.py
starexx/__main__.py
starexx/starexx.py
rstarexx-1.0.dist-info/METADATA
rstarexx-1.0.dist-info/WHEEL
rstarexx-1.0.dist-info/entry_points.txt
rstarexx-1.0.dist-info/top_level.txt
rstarexx-1.0.dist-info/RECORD
