Metadata-Version: 2.4
Name: rstarexx
Version: 1.0
Summary: Termux command execution server
Author: Starexx
Author-email: starexx.m@gmail.com
Requires-Python: >=3.7
License-File: LICENSE
Requires-Dist: Flask>=2.0.0
Dynamic: author
Dynamic: author-email
Dynamic: license-file
Dynamic: requires-dist
Dynamic: requires-python
Dynamic: summary
